Metadata-Version: 1.0
Name: jmgz-distributions
Version: 0.1
Summary: Gaussian jmgz_distributions
Home-page: UNKNOWN
Author: James Gachago
Author-email: myemail@someotherthing.com
License: UNKNOWN
Platform: UNKNOWN
